{
  "applinks": {
    "details": [
      {
        "appIDs": [
          "5NN7GUYB6T.chat.simplex.app"
        ],
        "components": [
          {
            "/": "/contact/*"
          },
          {
            "/": "/contact"
          },
          {
            "/": "/invitation/*"
          },
          {
            "/": "/invitation"
          },
          {
            "/": "/a/*"
          },
          {
            "/": "/a"
          },
          {
            "/": "/c/*"
          },
          {
            "/": "/c"
          },
          {
            "/": "/g/*"
          },
          {
            "/": "/g"
          },
          {
            "/": "/i/*"
          },
          {
            "/": "/i"
          }
        ]
      }
    ]
  }
}